langchain_classic/__init__.py
langchain_classic/base_language.py
langchain_classic/cache.py
langchain_classic/env.py
langchain_classic/example_generator.py
langchain_classic/formatting.py
langchain_classic/globals.py
langchain_classic/hub.py
langchain_classic/input.py
langchain_classic/model_laboratory.py
langchain_classic/py.typed
langchain_classic/python.py
langchain_classic/requests.py
langchain_classic/serpapi.py
langchain_classic/sql_database.py
langchain_classic/text_splitter.py
langchain_classic/_api/__init__.py
langchain_classic/_api/deprecation.py
langchain_classic/_api/interactive_env.py
langchain_classic/_api/module_import.py
langchain_classic/_api/path.py
langchain_classic/adapters/__init__.py
langchain_classic/adapters/openai.py
langchain_classic/agents/__init__.py
langchain_classic/agents/agent.py
langchain_classic/agents/agent_iterator.py
langchain_classic/agents/agent_types.py
langchain_classic/agents/initialize.py
langchain_classic/agents/load_tools.py
langchain_classic/agents/loading.py
langchain_classic/agents/schema.py
langchain_classic/agents/tools.py
langchain_classic/agents/types.py
langchain_classic/agents/utils.py
langchain_classic/agents/agent_toolkits/__init__.py
langchain_classic/agents/agent_toolkits/azure_cognitive_services.py
langchain_classic/agents/agent_toolkits/base.py
langchain_classic/agents/agent_toolkits/ainetwork/__init__.py
langchain_classic/agents/agent_toolkits/ainetwork/toolkit.py
langchain_classic/agents/agent_toolkits/amadeus/__init__.py
langchain_classic/agents/agent_toolkits/amadeus/toolkit.py
langchain_classic/agents/agent_toolkits/clickup/__init__.py
langchain_classic/agents/agent_toolkits/clickup/toolkit.py
langchain_classic/agents/agent_toolkits/conversational_retrieval/__init__.py
langchain_classic/agents/agent_toolkits/conversational_retrieval/openai_functions.py
langchain_classic/agents/agent_toolkits/conversational_retrieval/tool.py
langchain_classic/agents/agent_toolkits/csv/__init__.py
langchain_classic-1.0.0a1.dist-info/METADATA
langchain_classic-1.0.0a1.dist-info/WHEEL
langchain_classic-1.0.0a1.dist-info/licenses/LICENSE
langchain_classic-1.0.0a1.dist-info/RECORD
