Metadata-Version: 2.4
Name: langchain-classic
Version: 1.0.0a1
Summary: Building applications with LLMs through composability
Project-URL: Source Code, https://github.com/langchain-ai/langchain/tree/master/libs/langchain
Project-URL: Release Notes, https://github.com/langchain-ai/langchain/releases?q=tag%3A%22langchain%3D%3D0%22&expanded=true
Project-URL: repository, https://github.com/langchain-ai/langchain
License: MIT
License-File: LICENSE
Requires-Python: <4.0.0,>=3.10.0
Requires-Dist: async-timeout<5.0.0,>=4.0.0; python_version < '3.11'
Requires-Dist: langchain-core<2.0.0,>=1.0.0a7
Requires-Dist: langchain-text-splitters<2.0.0,>=1.0.0a1
Requires-Dist: langsmith<1.0.0,>=0.1.17
Requires-Dist: pydantic<3.0.0,>=2.7.4
Requires-Dist: pyyaml<7.0.0,>=5.3.0
Requires-Dist: requests<3.0.0,>=2.0.0
Requires-Dist: sqlalchemy<3.0.0,>=1.4.0
Provides-Extra: anthropic
Requires-Dist: langchain-anthropic; extra == 'anthropic'
Provides-Extra: aws
Requires-Dist: langchain-aws; extra == 'aws'
Provides-Extra: deepseek
Requires-Dist: langchain-deepseek; extra == 'deepseek'
Provides-Extra: fireworks
Requires-Dist: langchain-fireworks; extra == 'fireworks'
Provides-Extra: google-genai
Requires-Dist: langchain-google-genai; extra == 'google-genai'
Provides-Extra: google-vertexai
Requires-Dist: langchain-google-vertexai; extra == 'google-vertexai'
Provides-Extra: groq
Requires-Dist: langchain-groq; extra == 'groq'
Provides-Extra: mistralai
Requires-Dist: langchain-mistralai; extra == 'mistralai'
Provides-Extra: ollama
Requires-Dist: langchain-ollama; extra == 'ollama'
Provides-Extra: openai
Requires-Dist: langchain-openai; extra == 'openai'
Provides-Extra: perplexity
Requires-Dist: langchain-perplexity; extra == 'perplexity'
Provides-Extra: together
Requires-Dist: langchain-together; extra == 'together'
Provides-Extra: xai
Requires-Dist: langchain-xai; extra == 'xai'
